{
	"info": {
		"name": "Reference Architecture",
		"_postman_id": "2f01db2f-a510-a595-957c-34a0937df410",
		"description": "Created a collection that allows easy access to the Reference Architecture API endpoints.",
		"schema": "https://schema.getpostman.com/json/collection/v2.1.0/collection.json"
	},
	"item": [
		{
			"name": "Categories",
			"description": "",
			"item": [
				{
					"name": "Read all categories",
					"request": {
						"method": "GET",
						"header": [],
						"body": {
							"mode": "raw",
							"raw": "{\n  \"name\": \"Extra-large\"\n}"
						},
						"url": {
							"raw": "{{baseUrl}}/api/v1/categories",
							"host": [
								"{{baseUrl}}"
							],
							"path": [
								"api",
								"v1",
								"categories"
							]
						},
						"description": ""
					},
					"response": []
				},
				{
					"name": "Read a category",
					"request": {
						"method": "GET",
						"header": [],
						"body": {},
						"url": {
							"raw": "{{baseUrl}}/api/v1/categories/c5993571-e278-422f-a3e0-a262797fc63c",
							"host": [
								"{{baseUrl}}"
							],
							"path": [
								"api",
								"v1",
								"categories",
								"c5993571-e278-422f-a3e0-a262797fc63c"
							]
						},
						"description": ""
					},
					"response": []
				},
				{
					"name": "Create a category",
					"request": {
						"method": "POST",
						"header": [
							{
								"key": "Content-Type",
								"value": "application/json"
							},
							{
								"key": "Accept-Charset",
								"value": "utf-8"
							}
						],
						"body": {
							"mode": "raw",
							"raw": "{\n  \"name\": \"Sport Utility Vehicles\"\n}"
						},
						"url": {
							"raw": "{{baseUrl}}/api/v1/categories",
							"host": [
								"{{baseUrl}}"
							],
							"path": [
								"api",
								"v1",
								"categories"
							]
						},
						"description": ""
					},
					"response": []
				},
				{
					"name": "Change category name",
					"request": {
						"method": "PUT",
						"header": [
							{
								"key": "Content-Type",
								"value": "application/json"
							},
							{
								"key": "Accept-Charset",
								"value": "utf-8"
							}
						],
						"body": {
							"mode": "raw",
							"raw": "{\n\t\"id\": \"93661d8b-2b4c-410c-a4fd-36073be41e9b\",\n\t\"name\": \"Extra-large\",\n\t\"created\": \"2009-06-15T13:45:30.0000000Z\",\n\t\"notes\": [{}],\n\t\"subscribers\": [{}]\n}"
						},
						"url": {
							"raw": "{{baseUrl}}/api/v1/categories/93661d8b-2b4c-410c-a4fd-36073be41e9b",
							"host": [
								"{{baseUrl}}"
							],
							"path": [
								"api",
								"v1",
								"categories",
								"93661d8b-2b4c-410c-a4fd-36073be41e9b"
							]
						},
						"description": ""
					},
					"response": []
				}
			]
		},
		{
			"name": "Notes",
			"description": "",
			"item": []
		}
	]
}